portent/__init__.py
portent/data.py
portent/quotes.py
portent/welcomes.py
portent-0.0.2.dist-info/LICENSE
portent-0.0.2.dist-info/METADATA
portent-0.0.2.dist-info/WHEEL
portent-0.0.2.dist-info/top_level.txt
portent-0.0.2.dist-info/RECORD
