Metadata-Version: 2.1
Name: portent
Version: 0.0.2
Summary: Python package providing horrifying welcome messages for your application
Home-page: https://github.com/hypernormalisation/prologue
Author: Stephen Ogilvy
Author-email: sogilvy@tuta.io
License: UNKNOWN
Project-URL: Source, https://github.com/hypernormalisation/portent
Project-URL: Bug Reports, https://github.com/hypernormalisation/timbermafia/portent
Keywords: welcome
Platform: UNKNOWN
Classifier: Development Status :: 3 - Alpha
Classifier: Intended Audience :: Developers
Classifier: License :: OSI Approved :: GNU General Public License v3 or later (GPLv3+)
Classifier: Programming Language :: Python :: 3
Classifier: Programming Language :: Python :: 3.6
Classifier: Programming Language :: Python :: 3.7
Classifier: Programming Language :: Python :: 3.8
Requires-Python: >=3.6
